Qieyun/__init__.py
Qieyun/_utils.py
Qieyun/_書影.py
Qieyun/_韻圖.py
Qieyun/rhyme_book.csv
Qieyun/rhyme_table.csv
Qieyun/韻書.py
Qieyun/韻書和韻圖.py
qieyun-0.13.3.dist-info/LICENSE
qieyun-0.13.3.dist-info/METADATA
qieyun-0.13.3.dist-info/WHEEL
qieyun-0.13.3.dist-info/top_level.txt
qieyun-0.13.3.dist-info/RECORD
