Metadata-Version: 2.1
Name: qieyun
Version: 0.13.3
Summary: A Python library for the Qieyun phonological system
Home-page: https://github.com/nk2028/qieyun-python
Author: The nk2028 Project
Author-email: support@nk2028.shn.hk
License: UNKNOWN
Project-URL: Bug Reports, https://github.com/nk2028/qieyun-python/issues
Project-URL: Source, https://github.com/nk2028/qieyun-python
Keywords: middle-chinese historical-linguistics qieyun
Platform: UNKNOWN
Classifier: Development Status :: 4 - Beta
Classifier: Intended Audience :: Developers
Classifier: Topic :: Software Development :: Libraries :: Python Modules
Classifier: Topic :: Text Processing :: Linguistic
Classifier: Natural Language :: Chinese (Traditional)
Classifier: License :: CC0 1.0 Universal (CC0 1.0) Public Domain Dedication
Classifier: Programming Language :: Python :: 3
Classifier: Programming Language :: Python :: 3.6
Classifier: Programming Language :: Python :: 3.7
Classifier: Programming Language :: Python :: 3.8
Classifier: Programming Language :: Python :: 3.9
Requires-Python: >=3.6, <4
Requires-Dist: qieyun-encoder (<0.5,>=0.4)
Requires-Dist: networkx (<2.6,>=2.5)
